masurvival/metrics.py
masurvival/preprocessing.py
masurvival/util.py
masurvival/functions.py
masurvival/exceptions.py
masurvival/nonparametric.py
masurvival/testing.py
masurvival/docstrings.py
masurvival/column.py
masurvival/__init__.py
masurvival/compare.py
masurvival/base.py
masurvival/svm/_minlip.cpython-313-x86_64-linux-gnu.so
masurvival/svm/minlip.py
masurvival/svm/naive_survival_svm.py
masurvival/svm/_prsvm.cpython-313-x86_64-linux-gnu.so
masurvival/svm/__init__.py
masurvival/svm/survival_svm.py
masurvival/meta/stacking.py
masurvival/meta/ensemble_selection.py
masurvival/meta/__init__.py
masurvival/meta/base.py
masurvival/ensemble/_coxph_loss.cpython-313-x86_64-linux-gnu.so
masurvival/ensemble/survival_loss.py
masurvival/ensemble/forest.py
masurvival/ensemble/boosting.py
masurvival/ensemble/__init__.py
masurvival/datasets/__init__.py
masurvival/datasets/base.py
masurvival/datasets/data/breast_cancer_GSE7390-metastasis.arff
masurvival/datasets/data/whas500.arff
masurvival/datasets/data/flchain.arff
masurvival/datasets/data/veteran.arff
masurvival/datasets/data/cgvhd.arff
masurvival/datasets/data/GBSG2.arff
masurvival/datasets/data/bmt.arff
masurvival/datasets/data/actg320.arff
masurvival/io/arffread.py
masurvival/io/arffwrite.py
masurvival/io/__init__.py
masurvival/linear_model/coxph.py
masurvival/linear_model/_coxnet.cpython-313-x86_64-linux-gnu.so
masurvival/linear_model/coxnet.py
masurvival/linear_model/aft.py
masurvival/linear_model/__init__.py
masurvival/tree/_tree.cpython-313-x86_64-linux-gnu.so
masurvival/tree/_criterion.cpython-313-x86_64-linux-gnu.so
masurvival/tree/tree.py
masurvival/tree/_splitter.cpython-313-x86_64-linux-gnu.so
masurvival/tree/__init__.py
masurvival/tree/_classes.py
masurvival/bintrees/_binarytrees.cpython-313-x86_64-linux-gnu.so
masurvival/bintrees/__init__.py
masurvival/kernels/clinical.py
masurvival/kernels/_clinical_kernel.cpython-313-x86_64-linux-gnu.so
masurvival-0.1.2.dist-info/WHEEL
masurvival-0.1.2.dist-info/top_level.txt
masurvival-0.1.2.dist-info/METADATA
masurvival-0.1.2.dist-info/RECORD
masurvival-0.1.2.dist-info/licenses/COPYING
