Metadata-Version: 2.4
Name: masurvival
Version: 0.1.2
Summary: MASurvival: Missingness-Avoiding Survival Forest - An extension of scikit-survival with missingness-avoidance regularization for handling missing data in survival analysis
Author: Aneta Lisowska
License-Expression: GPL-3.0-or-later
Project-URL: Homepage, https://github.com/anli66/masurvival
Project-URL: Source Code, https://github.com/anli66/masurvival
Classifier: Development Status :: 4 - Beta
Classifier: Intended Audience :: Science/Research
Classifier: Intended Audience :: Developers
Classifier: Operating System :: MacOS
Classifier: Operating System :: Microsoft :: Windows
Classifier: Operating System :: POSIX
Classifier: Programming Language :: C++
Classifier: Programming Language :: Cython
Classifier: Programming Language :: Python
Classifier: Programming Language :: Python :: 3
Classifier: Programming Language :: Python :: 3.10
Classifier: Programming Language :: Python :: 3.11
Classifier: Programming Language :: Python :: 3.12
Classifier: Programming Language :: Python :: 3.13
Classifier: Topic :: Software Development
Classifier: Topic :: Scientific/Engineering
Requires-Python: >=3.10
License-File: COPYING
Requires-Dist: ecos
Requires-Dist: joblib
Requires-Dist: numexpr
Requires-Dist: numpy
Requires-Dist: osqp>=1.0.2
Requires-Dist: pandas>=2.0.0
Requires-Dist: scipy>=1.3.2
Requires-Dist: scikit-learn<1.8,>=1.6.1
Dynamic: license-file
